CHANGELOG
LICENSE
MANIFEST.in
README.md
setup.py
flask_wechat_auth.egg-info/PKG-INFO
flask_wechat_auth.egg-info/SOURCES.txt
flask_wechat_auth.egg-info/dependency_links.txt
flask_wechat_auth.egg-info/requires.txt
flask_wechat_auth.egg-info/top_level.txt
mod_wechat/__init__.py
mod_wechat/controllers.py
mod_wechat/models.py