Metadata-Version: 1.1
Name: flask-wechat-auth
Version: 0.0.1
Summary: WeChat Flask Blueprint Module
Home-page: https://github.com/hitakaken/flask-wechat.git
Author: CaoKe
Author-email: hitakaken@gmail.com
License: MIT License
